leapyearmodule/__init__.py
leapyearmodule/leapyearmodule.py
tests/__init__.py
tests/test_leapyearmodule.py
leapyearmodule-0.1.0.dist-info/LICENSE
leapyearmodule-0.1.0.dist-info/METADATA
leapyearmodule-0.1.0.dist-info/WHEEL
leapyearmodule-0.1.0.dist-info/top_level.txt
leapyearmodule-0.1.0.dist-info/RECORD
